easyapi/__init__.py
easyapi/base.py
easyapi/calc.py
easyapi/calc_resource.py
easyapi/constants.py
easyapi/dates.py
easyapi/exception.py
easyapi/filters.py
easyapi/middleware.py
easyapi/rate_limit.py
easyapi/routes.py
easyapi/util.py
easyapi/orm/__init__.py
easyapi/tenant/__init__.py
easyapi/tenant/db_router.py
easyapi/tenant/tenant.py
easyapi_django-0.25.dist-info/licenses/LICENSE
easyapi_django-0.25.dist-info/METADATA
easyapi_django-0.25.dist-info/WHEEL
easyapi_django-0.25.dist-info/top_level.txt
easyapi_django-0.25.dist-info/RECORD
