Metadata-Version: 2.4
Name: easyapi_django
Version: 0.25
Summary: A simple rest api generator for django based on models
Author-email: Stamatios Stamou Jr <bushier.outsets.0c@icloud.com>
License: MIT
Project-URL: Homepage, https://github.com/ssjunior/easyapi-django
Project-URL: Bug Tracker, https://github.com/ssjunior/easyapi-django/issues
Classifier: Programming Language :: Python :: 3
Classifier: Operating System :: OS Independent
Requires-Python: >=3.7
License-File: LICENSE
Dynamic: license-file
